# Comparing `tmp/librenv-0.1.2-py3.11.egg` & `tmp/librenv-0.1.3-py3.11.egg`

## zipinfo {}

```diff
@@ -1,28 +1,32 @@
-Zip file size: 16314 bytes, number of entries: 26
--rw-r--r--  2.0 unx      762 b- defN 23-May-13 15:54 EGG-INFO/PKG-INFO
--rw-r--r--  2.0 unx      396 b- defN 23-May-13 15:54 EGG-INFO/SOURCES.txt
--rw-r--r--  2.0 unx        1 b- defN 23-May-13 15:54 EGG-INFO/dependency_links.txt
--rw-r--r--  2.0 unx       50 b- defN 23-May-13 15:54 EGG-INFO/entry_points.txt
--rw-r--r--  2.0 unx        8 b- defN 23-May-13 15:54 EGG-INFO/top_level.txt
--rw-r--r--  2.0 unx        1 b- defN 23-May-13 15:54 EGG-INFO/zip-safe
--rw-r--r--  2.0 unx       83 b- defN 23-May-13 15:49 librenv/__init__.py
+Zip file size: 19415 bytes, number of entries: 30
+-rw-r--r--  2.0 unx      762 b- defN 23-May-13 17:12 EGG-INFO/PKG-INFO
+-rw-r--r--  2.0 unx      420 b- defN 23-May-13 17:12 EGG-INFO/SOURCES.txt
+-rw-r--r--  2.0 unx        1 b- defN 23-May-13 17:12 EGG-INFO/dependency_links.txt
+-rw-r--r--  2.0 unx       50 b- defN 23-May-13 17:12 EGG-INFO/entry_points.txt
+-rw-r--r--  2.0 unx        8 b- defN 23-May-13 17:12 EGG-INFO/top_level.txt
+-rw-r--r--  2.0 unx        1 b- defN 23-May-13 17:12 EGG-INFO/zip-safe
+-rw-r--r--  2.0 unx       83 b- defN 23-May-13 17:10 librenv/__init__.py
 -rw-r--r--  2.0 unx      258 b- defN 23-May-13 12:35 librenv/__main__.py
 -rw-r--r--  2.0 unx     2399 b- defN 23-May-13 15:54 librenv/librenv.py
 -rw-r--r--  2.0 unx     2019 b- defN 23-May-13 15:47 librenv/project.py
--rw-r--r--  2.0 unx      258 b- defN 23-May-13 15:54 librenv/__pycache__/__init__.cpython-311.pyc
--rw-r--r--  2.0 unx      866 b- defN 23-May-13 15:54 librenv/__pycache__/__main__.cpython-311.pyc
--rw-r--r--  2.0 unx     5328 b- defN 23-May-13 15:54 librenv/__pycache__/librenv.cpython-311.pyc
--rw-r--r--  2.0 unx     3496 b- defN 23-May-13 15:54 librenv/__pycache__/project.cpython-311.pyc
--rw-r--r--  2.0 unx      136 b- defN 23-May-13 13:38 librenv/api/__init__.py
--rw-r--r--  2.0 unx      349 b- defN 23-May-11 10:42 librenv/api/color.py
+-rw-r--r--  2.0 unx      258 b- defN 23-May-13 17:12 librenv/__pycache__/__init__.cpython-311.pyc
+-rw-r--r--  2.0 unx      866 b- defN 23-May-13 17:12 librenv/__pycache__/__main__.cpython-311.pyc
+-rw-r--r--  2.0 unx     5328 b- defN 23-May-13 17:12 librenv/__pycache__/librenv.cpython-311.pyc
+-rw-r--r--  2.0 unx     3496 b- defN 23-May-13 17:12 librenv/__pycache__/project.cpython-311.pyc
+-rw-r--r--  2.0 unx      134 b- defN 23-May-13 17:10 librenv/api/__init__.py
+-rw-r--r--  2.0 unx      499 b- defN 23-May-13 17:08 librenv/api/character.py
+-rw-r--r--  2.0 unx      524 b- defN 23-May-13 17:07 librenv/api/color.py
 -rw-r--r--  2.0 unx      324 b- defN 23-May-13 14:42 librenv/api/drawable.py
+-rw-r--r--  2.0 unx      539 b- defN 23-May-13 17:09 librenv/api/image.py
 -rw-r--r--  2.0 unx      539 b- defN 23-May-13 14:42 librenv/api/sprite.py
 -rw-r--r--  2.0 unx      641 b- defN 23-May-13 14:40 librenv/api/text.py
 -rw-r--r--  2.0 unx      503 b- defN 23-May-13 15:49 librenv/api/vector2.py
--rw-r--r--  2.0 unx      424 b- defN 23-May-13 15:54 librenv/api/__pycache__/__init__.cpython-311.pyc
--rw-r--r--  2.0 unx     1369 b- defN 23-May-13 15:54 librenv/api/__pycache__/color.cpython-311.pyc
--rw-r--r--  2.0 unx     1187 b- defN 23-May-13 15:54 librenv/api/__pycache__/drawable.cpython-311.pyc
--rw-r--r--  2.0 unx     1617 b- defN 23-May-13 15:54 librenv/api/__pycache__/sprite.cpython-311.pyc
--rw-r--r--  2.0 unx     1786 b- defN 23-May-13 15:54 librenv/api/__pycache__/text.cpython-311.pyc
--rw-r--r--  2.0 unx     1347 b- defN 23-May-13 15:54 librenv/api/__pycache__/vector2.cpython-311.pyc
-26 files, 26147 bytes uncompressed, 12748 bytes compressed:  51.2%
+-rw-r--r--  2.0 unx      422 b- defN 23-May-13 17:12 librenv/api/__pycache__/__init__.cpython-311.pyc
+-rw-r--r--  2.0 unx     1084 b- defN 23-May-13 17:12 librenv/api/__pycache__/character.cpython-311.pyc
+-rw-r--r--  2.0 unx     2256 b- defN 23-May-13 17:12 librenv/api/__pycache__/color.cpython-311.pyc
+-rw-r--r--  2.0 unx     1187 b- defN 23-May-13 17:12 librenv/api/__pycache__/drawable.cpython-311.pyc
+-rw-r--r--  2.0 unx     1614 b- defN 23-May-13 17:12 librenv/api/__pycache__/image.cpython-311.pyc
+-rw-r--r--  2.0 unx     1617 b- defN 23-May-13 17:12 librenv/api/__pycache__/sprite.cpython-311.pyc
+-rw-r--r--  2.0 unx     1786 b- defN 23-May-13 17:12 librenv/api/__pycache__/text.cpython-311.pyc
+-rw-r--r--  2.0 unx     1347 b- defN 23-May-13 17:12 librenv/api/__pycache__/vector2.cpython-311.pyc
+30 files, 30965 bytes uncompressed, 15269 bytes compressed:  50.7%
```

## zipnote «TEMP»/diffoscope_se88vtim_/tmp5_cuqtaf_.zip

```diff
@@ -39,38 +39,50 @@
 
 Filename: librenv/__pycache__/project.cpython-311.pyc
 Comment: 
 
 Filename: librenv/api/__init__.py
 Comment: 
 
+Filename: librenv/api/character.py
+Comment: 
+
 Filename: librenv/api/color.py
 Comment: 
 
 Filename: librenv/api/drawable.py
 Comment: 
 
+Filename: librenv/api/image.py
+Comment: 
+
 Filename: librenv/api/sprite.py
 Comment: 
 
 Filename: librenv/api/text.py
 Comment: 
 
 Filename: librenv/api/vector2.py
 Comment: 
 
 Filename: librenv/api/__pycache__/__init__.cpython-311.pyc
 Comment: 
 
+Filename: librenv/api/__pycache__/character.cpython-311.pyc
+Comment: 
+
 Filename: librenv/api/__pycache__/color.cpython-311.pyc
 Comment: 
 
 Filename: librenv/api/__pycache__/drawable.cpython-311.pyc
 Comment: 
 
+Filename: librenv/api/__pycache__/image.cpython-311.pyc
+Comment: 
+
 Filename: librenv/api/__pycache__/sprite.cpython-311.pyc
 Comment: 
 
 Filename: librenv/api/__pycache__/text.cpython-311.pyc
 Comment: 
 
 Filename: librenv/api/__pycache__/vector2.cpython-311.pyc
```

## EGG-INFO/PKG-INFO

```diff
@@ -1,10 +1,10 @@
 Metadata-Version: 2.1
 Name: librenv
-Version: 0.1.2
+Version: 0.1.3
 Summary: Simple visual novel engine, written on Python3+SDL2.
 Home-page: https://notabug.org/loliconshik3/librenv
 Author: loliconshik3
 Description-Content-Type: text/markdown
 License-File: LICENSE
 
 # librenv
```

## EGG-INFO/SOURCES.txt

```diff
@@ -7,12 +7,13 @@
 librenv/project.py
 librenv.egg-info/PKG-INFO
 librenv.egg-info/SOURCES.txt
 librenv.egg-info/dependency_links.txt
 librenv.egg-info/entry_points.txt
 librenv.egg-info/top_level.txt
 librenv/api/__init__.py
+librenv/api/character.py
 librenv/api/color.py
 librenv/api/drawable.py
-librenv/api/sprite.py
+librenv/api/image.py
 librenv/api/text.py
 librenv/api/vector2.py
```

## librenv/__init__.py

```diff
@@ -1,4 +1,4 @@
 """
 Simple visual novel engine, written on Python3+SDL2.
 """
-__version__ = "0.1.2"
+__version__ = "0.1.3"
```

## librenv/__pycache__/__init__.cpython-311.pyc

### Python bytecode

```diff
@@ -1,28 +1,28 @@
 magic:    0xa70d0d0a
-moddate:  0x64875f64 (Sat May 13 12:49:40 2023 UTC)
+moddate:  0x4c9a5f64 (Sat May 13 14:10:20 2023 UTC)
 files sz: 83
 code
    argcount  : 0
    nlocals   : 0
    stacksize : 1
    flags     : 0
    code 0x970064005a0064015a0164025300
      0           0 RESUME                   0
    
      1           2 LOAD_CONST               0 ('\nSimple visual novel engine, written on Python3+SDL2.\n')
                  4 STORE_NAME               0 (__doc__)
    
-     4           6 LOAD_CONST               1 ('0.1.2')
+     4           6 LOAD_CONST               1 ('0.1.3')
                  8 STORE_NAME               1 (__version__)
                 10 LOAD_CONST               2 (None)
                 12 RETURN_VALUE
    consts
       '\nSimple visual novel engine, written on Python3+SDL2.\n'
-      '0.1.2'
+      '0.1.3'
       None
    names      ('__doc__', '__version__')
    varnames   ()
    freevars   ()
    cellvars   ()
    filename   'build/bdist.linux-x86_64/egg/librenv/__init__.py'
    name       '<module>'
```

## librenv/api/__init__.py

```diff
@@ -1,6 +1,6 @@
 from .drawable import Drawable
 from .vector2 import Vector2
 from .color import Color
-from .sprite import Sprite
+from .image import Image
 from .text import Text
```

## librenv/api/color.py

```diff
@@ -1,18 +1,20 @@
-
+import colorsys
 
 class Color:
 
-    def __init__(self, r: int, g: int, b: int, a: int=255) -> None:
+    def __init__(self, r: int=255, g: int=255, b: int=255, a: int=255) -> None:
         self.r = int(r)
         self.g = int(g)
         self.b = int(b)
         self.a = int(a)
 
     @staticmethod
     def from_hsv(h: int, s: int, v: int):
-        return Color(0,0,0)
+        r, g, b = tuple(round(i * 255) for i in colorsys.hsv_to_rgb(h,s,v))
+        return Color(r, g, b)
 
     @staticmethod
     def from_hex(hex_str: str):
-        return Color(0,0,0)
+        r, g, b = tuple(int(hex_str[i:i+2], 16) for i in (0, 2, 4))
+        return Color(r, g, b)
```

## librenv/api/__pycache__/__init__.cpython-311.pyc

### Python bytecode

```diff
@@ -1,10 +1,10 @@
 magic:    0xa70d0d0a
-moddate:  0xa4685f64 (Sat May 13 10:38:28 2023 UTC)
-files sz: 136
+moddate:  0x459a5f64 (Sat May 13 14:10:13 2023 UTC)
+files sz: 134
 code
    argcount  : 0
    nlocals   : 0
    stacksize : 2
    flags     : 0
    code
       0x9700640064016c006d015a010100640064026c026d035a030100640064
@@ -30,18 +30,18 @@
                 28 LOAD_CONST               3 (('Color',))
                 30 IMPORT_NAME              4 (color)
                 32 IMPORT_FROM              5 (Color)
                 34 STORE_NAME               5 (Color)
                 36 POP_TOP
    
      4          38 LOAD_CONST               0 (1)
-                40 LOAD_CONST               4 (('Sprite',))
-                42 IMPORT_NAME              6 (sprite)
-                44 IMPORT_FROM              7 (Sprite)
-                46 STORE_NAME               7 (Sprite)
+                40 LOAD_CONST               4 (('Image',))
+                42 IMPORT_NAME              6 (image)
+                44 IMPORT_FROM              7 (Image)
+                46 STORE_NAME               7 (Image)
                 48 POP_TOP
    
      5          50 LOAD_CONST               0 (1)
                 52 LOAD_CONST               5 (('Text',))
                 54 IMPORT_NAME              8 (text)
                 56 IMPORT_FROM              9 (Text)
                 58 STORE_NAME               9 (Text)
@@ -49,18 +49,18 @@
                 62 LOAD_CONST               6 (None)
                 64 RETURN_VALUE
    consts
       1
       ('Drawable',)
       ('Vector2',)
       ('Color',)
-      ('Sprite',)
+      ('Image',)
       ('Text',)
       None
-   names      ('drawable', 'Drawable', 'vector2', 'Vector2', 'color', 'Color', 'sprite', 'Sprite', 'text', 'Text')
+   names      ('drawable', 'Drawable', 'vector2', 'Vector2', 'color', 'Color', 'image', 'Image', 'text', 'Text')
    varnames   ()
    freevars   ()
    cellvars   ()
    filename   'build/bdist.linux-x86_64/egg/librenv/api/__init__.py'
    name       '<module>'
    firstlineno 1
    lnotab 0x00ff02010c010c010c010c01
```

## librenv/api/__pycache__/color.cpython-311.pyc

### Python bytecode

```diff
@@ -1,31 +1,38 @@
 magic:    0xa70d0d0a
-moddate:  0x699c5c64 (Thu May 11 07:42:33 2023 UTC)
-files sz: 349
+moddate:  0xae995f64 (Sat May 13 14:07:42 2023 UTC)
+files sz: 524
 code
    argcount  : 0
    nlocals   : 0
    stacksize : 4
    flags     : 0
    code
-      0x970002004700640084006401a6020000ab0200000000000000005a0064
-      025300
+      0x9700640064016c005a0002004700640284006403a6020000ab02000000
+      00000000005a0164015300
      0           0 RESUME                   0
    
-     3           2 PUSH_NULL
-                 4 LOAD_BUILD_CLASS
-                 6 LOAD_CONST               0 (<code object Color, file "build/bdist.linux-x86_64/egg/librenv/api/color.py", line 3>)
-                 8 MAKE_FUNCTION            0
-                10 LOAD_CONST               1 ('Color')
-                12 PRECALL                  2
-                16 CALL                     2
-                26 STORE_NAME               0 (Color)
-                28 LOAD_CONST               2 (None)
-                30 RETURN_VALUE
+     1           2 LOAD_CONST               0 (0)
+                 4 LOAD_CONST               1 (None)
+                 6 IMPORT_NAME              0 (colorsys)
+                 8 STORE_NAME               0 (colorsys)
+   
+     3          10 PUSH_NULL
+                12 LOAD_BUILD_CLASS
+                14 LOAD_CONST               2 (<code object Color, file "build/bdist.linux-x86_64/egg/librenv/api/color.py", line 3>)
+                16 MAKE_FUNCTION            0
+                18 LOAD_CONST               3 ('Color')
+                20 PRECALL                  2
+                24 CALL                     2
+                34 STORE_NAME               1 (Color)
+                36 LOAD_CONST               1 (None)
+                38 RETURN_VALUE
    consts
+      0
+      None
       code
          argcount  : 0
          nlocals   : 0
          stacksize : 11
          flags     : 0
          code
             0x970065005a0164005a02640f6402650364036503640465036405650364
@@ -34,15 +41,15 @@
             000000ab0000000000000000005a0864075300
            3           0 RESUME                   0
                        2 LOAD_NAME                0 (__name__)
                        4 STORE_NAME               1 (__module__)
                        6 LOAD_CONST               0 ('Color')
                        8 STORE_NAME               2 (__qualname__)
          
-           5          10 LOAD_CONST              15 ((255,))
+           5          10 LOAD_CONST              15 ((255, 255, 255, 255))
                       12 LOAD_CONST               2 ('r')
                       14 LOAD_NAME                3 (int)
                       16 LOAD_CONST               3 ('g')
                       18 LOAD_NAME                3 (int)
                       20 LOAD_CONST               4 ('b')
                       22 LOAD_NAME                3 (int)
                       24 LOAD_CONST               5 ('a')
@@ -67,26 +74,26 @@
                       58 MAKE_FUNCTION            4 (annotations)
          
           11          60 PRECALL                  0
                       64 CALL                     0
          
           12          74 STORE_NAME               6 (from_hsv)
          
-          15          76 LOAD_NAME                5 (staticmethod)
+          16          76 LOAD_NAME                5 (staticmethod)
          
-          16          78 LOAD_CONST              13 ('hex_str')
+          17          78 LOAD_CONST              13 ('hex_str')
                       80 LOAD_NAME                7 (str)
                       82 BUILD_TUPLE              2
-                      84 LOAD_CONST              14 (<code object from_hex, file "build/bdist.linux-x86_64/egg/librenv/api/color.py", line 15>)
+                      84 LOAD_CONST              14 (<code object from_hex, file "build/bdist.linux-x86_64/egg/librenv/api/color.py", line 16>)
                       86 MAKE_FUNCTION            4 (annotations)
          
-          15          88 PRECALL                  0
+          16          88 PRECALL                  0
                       92 CALL                     0
          
-          16         102 STORE_NAME               8 (from_hex)
+          17         102 STORE_NAME               8 (from_hex)
                      104 LOAD_CONST               7 (None)
                      106 RETURN_VALUE
          consts
             'Color'
             255
             'r'
             'g'
@@ -148,81 +155,205 @@
                firstlineno 5
                lnotab 0x0201280128012801
             'h'
             's'
             'v'
             code
                argcount  : 3
-               nlocals   : 3
-               stacksize : 5
+               nlocals   : 6
+               stacksize : 8
                flags     : 3
                code
-                  0x9700740100000000000000000000640164016401a6030000ab03000000
-                  00000000005300
+                  0x9700740100000000000000000000640184007403000000000000000000
+                  006a0200000000000000007c007c017c02a6030000ab0300000000000000
+                  004400a6000000ab000000000000000000a6010000ab0100000000000000
+                  005c0300007d037d047d057407000000000000000000007c037c047c05a6
+                  030000ab0300000000000000005300
                 11           0 RESUME                   0
                
-                13           2 LOAD_GLOBAL              1 (NULL + Color)
-                            14 LOAD_CONST               1 (0)
-                            16 LOAD_CONST               1 (0)
-                            18 LOAD_CONST               1 (0)
-                            20 PRECALL                  3
-                            24 CALL                     3
-                            34 RETURN_VALUE
+                13           2 LOAD_GLOBAL              1 (NULL + tuple)
+                            14 LOAD_CONST               1 (<code object <genexpr>, file "build/bdist.linux-x86_64/egg/librenv/api/color.py", line 13>)
+                            16 MAKE_FUNCTION            0
+                            18 LOAD_GLOBAL              3 (NULL + colorsys)
+                            30 LOAD_ATTR                2 (hsv_to_rgb)
+                            40 LOAD_FAST                0 (h)
+                            42 LOAD_FAST                1 (s)
+                            44 LOAD_FAST                2 (v)
+                            46 PRECALL                  3
+                            50 CALL                     3
+                            60 GET_ITER
+                            62 PRECALL                  0
+                            66 CALL                     0
+                            76 PRECALL                  1
+                            80 CALL                     1
+                            90 UNPACK_SEQUENCE          3
+                            94 STORE_FAST               3 (r)
+                            96 STORE_FAST               4 (g)
+                            98 STORE_FAST               5 (b)
+               
+                14         100 LOAD_GLOBAL              7 (NULL + Color)
+                           112 LOAD_FAST                3 (r)
+                           114 LOAD_FAST                4 (g)
+                           116 LOAD_FAST                5 (b)
+                           118 PRECALL                  3
+                           122 CALL                     3
+                           132 RETURN_VALUE
                consts
                   None
-                  0
-               names      ('Color',)
-               varnames   ('h', 's', 'v')
+                  code
+                     argcount  : 1
+                     nlocals   : 2
+                     stacksize : 5
+                     flags     : 51
+                     code
+                        0x4b00010097007c005d167d017401000000000000000000007c0164007a
+                        050000a6010000ab0100000000000000005600970101008c1764015300
+                      13           0 RETURN_GENERATOR
+                                   2 POP_TOP
+                                   4 RESUME                   0
+                                   6 LOAD_FAST                0 (.0)
+                             >>    8 FOR_ITER                22 (to 54)
+                                  10 STORE_FAST               1 (i)
+                                  12 LOAD_GLOBAL              1 (NULL + round)
+                                  24 LOAD_FAST                1 (i)
+                                  26 LOAD_CONST               0 (255)
+                                  28 BINARY_OP                5 (*)
+                                  32 PRECALL                  1
+                                  36 CALL                     1
+                                  46 YIELD_VALUE
+                                  48 RESUME                   1
+                                  50 POP_TOP
+                                  52 JUMP_BACKWARD           23 (to 8)
+                             >>   54 LOAD_CONST               1 (None)
+                                  56 RETURN_VALUE
+                     consts
+                        255
+                        None
+                     names      ('round',)
+                     varnames   ('.0', 'i')
+                     freevars   ()
+                     cellvars   ()
+                     filename   'build/bdist.linux-x86_64/egg/librenv/api/color.py'
+                     name       '<genexpr>'
+                     firstlineno 13
+                     lnotab 0x
+               names      ('tuple', 'colorsys', 'hsv_to_rgb', 'Color')
+               varnames   ('h', 's', 'v', 'r', 'g', 'b')
                freevars   ()
                cellvars   ()
                filename   'build/bdist.linux-x86_64/egg/librenv/api/color.py'
                name       'from_hsv'
                firstlineno 11
-               lnotab 0x0202
+               lnotab 0x02026201
             'hex_str'
             code
                argcount  : 1
-               nlocals   : 1
+               nlocals   : 4
                stacksize : 5
                flags     : 3
                code
-                  0x9700740100000000000000000000640164016401a6030000ab03000000
-                  00000000005300
-                15           0 RESUME                   0
-               
-                17           2 LOAD_GLOBAL              1 (NULL + Color)
-                            14 LOAD_CONST               1 (0)
-                            16 LOAD_CONST               1 (0)
-                            18 LOAD_CONST               1 (0)
-                            20 PRECALL                  3
-                            24 CALL                     3
-                            34 RETURN_VALUE
+                  0x87009700740100000000000000000000880066016401840864024400a6
+                  000000ab000000000000000000a6010000ab0100000000000000005c0300
+                  007d017d027d037403000000000000000000007c017c027c03a6030000ab
+                  0300000000000000005300
+                             0 MAKE_CELL                0 (hex_str)
+               
+                16           2 RESUME                   0
+               
+                18           4 LOAD_GLOBAL              1 (NULL + tuple)
+                            16 LOAD_CLOSURE             0 (hex_str)
+                            18 BUILD_TUPLE              1
+                            20 LOAD_CONST               1 (<code object <genexpr>, file "build/bdist.linux-x86_64/egg/librenv/api/color.py", line 18>)
+                            22 MAKE_FUNCTION            8 (closure)
+                            24 LOAD_CONST               2 ((0, 2, 4))
+                            26 GET_ITER
+                            28 PRECALL                  0
+                            32 CALL                     0
+                            42 PRECALL                  1
+                            46 CALL                     1
+                            56 UNPACK_SEQUENCE          3
+                            60 STORE_FAST               1 (r)
+                            62 STORE_FAST               2 (g)
+                            64 STORE_FAST               3 (b)
+               
+                19          66 LOAD_GLOBAL              3 (NULL + Color)
+                            78 LOAD_FAST                1 (r)
+                            80 LOAD_FAST                2 (g)
+                            82 LOAD_FAST                3 (b)
+                            84 PRECALL                  3
+                            88 CALL                     3
+                            98 RETURN_VALUE
                consts
                   None
-                  0
-               names      ('Color',)
-               varnames   ('hex_str',)
+                  code
+                     argcount  : 1
+                     nlocals   : 2
+                     stacksize : 7
+                     flags     : 51
+                     code
+                        0x95014b00010097007c005d1f7d0174010000000000000000000089027c
+                        017c0164007a0000008502190000000000000000006401a6020000ab0200
+                        000000000000005600970101008c2064025300
+                                   0 COPY_FREE_VARS           1
+                     
+                      18           2 RETURN_GENERATOR
+                                   4 POP_TOP
+                                   6 RESUME                   0
+                                   8 LOAD_FAST                0 (.0)
+                             >>   10 FOR_ITER                31 (to 74)
+                                  12 STORE_FAST               1 (i)
+                                  14 LOAD_GLOBAL              1 (NULL + int)
+                                  26 LOAD_DEREF               2 (hex_str)
+                                  28 LOAD_FAST                1 (i)
+                                  30 LOAD_FAST                1 (i)
+                                  32 LOAD_CONST               0 (2)
+                                  34 BINARY_OP                0 (+)
+                                  38 BUILD_SLICE              2
+                                  40 BINARY_SUBSCR
+                                  50 LOAD_CONST               1 (16)
+                                  52 PRECALL                  2
+                                  56 CALL                     2
+                                  66 YIELD_VALUE
+                                  68 RESUME                   1
+                                  70 POP_TOP
+                                  72 JUMP_BACKWARD           32 (to 10)
+                             >>   74 LOAD_CONST               2 (None)
+                                  76 RETURN_VALUE
+                     consts
+                        2
+                        16
+                        None
+                     names      ('int',)
+                     varnames   ('.0', 'i')
+                     freevars   ('hex_str',)
+                     cellvars   ()
+                     filename   'build/bdist.linux-x86_64/egg/librenv/api/color.py'
+                     name       '<genexpr>'
+                     firstlineno 18
+                     lnotab 0x
+                  (0, 2, 4)
+               names      ('tuple', 'Color')
+               varnames   ('hex_str', 'r', 'g', 'b')
                freevars   ()
-               cellvars   ()
+               cellvars   ('hex_str',)
                filename   'build/bdist.linux-x86_64/egg/librenv/api/color.py'
                name       'from_hex'
-               firstlineno 15
-               lnotab 0x0202
-            (255,)
+               firstlineno 16
+               lnotab 0x04023e01
+            (255, 255, 255, 255)
          names      ('__name__', '__module__', '__qualname__', 'int', '__init__', 'staticmethod', 'from_hsv', 'str', 'from_hex')
          varnames   ()
          freevars   ()
          cellvars   ()
          filename   'build/bdist.linux-x86_64/egg/librenv/api/color.py'
          name       'Color'
          firstlineno 3
-         lnotab 0x0a021e06020112ff0e01020302010aff0e01
+         lnotab 0x0a021e06020112ff0e01020402010aff0e01
       'Color'
-      None
-   names      ('Color',)
+   names      ('colorsys', 'Color')
    varnames   ()
    freevars   ()
    cellvars   ()
    filename   'build/bdist.linux-x86_64/egg/librenv/api/color.py'
    name       '<module>'
    firstlineno 1
-   lnotab 0x00ff0203
+   lnotab 0x00ff02010802
```

